{
  "__Vehicle__": {
    "vid": "20",
    "user": "\uc724\ud765\uc5f4",
    "social_activities": {
      "info": {
        "response": 10,
        "received_data": 10,
        "not_used_data": 1,
        "redistributed_data": 8
      },
      "scoring": 1.0,
      "ignoring": 0.1,
      "sharing": 0.8
    },
    "VDI": {
      "createdData": [
        {
          "contents": "\"<\uae34\uae09> \uacbd\uc778\ub85c \uc1a1\ub0b4\uc0ac\uac70\ub9ac\uc5d0\uc11c \uc2ec\uace1\uace0\uac00\uc0ac\uac70\ub9ac\ubc29\ud5a5, \uc2ec\uace1\uace0\uac00\uc0ac\uac70\ub9ac 70m \uc815\ub3c4 \ubabb \uac04 \uc9c0\uc810 3\ucc28\ub85c\uc5d0\uc11c \uc2b9\uc6a9\ucc28\uac04\uc758 \ucd94\ub3cc\uc0ac\uace0\uac00 \uc77c\uc5b4\ub098, \uc544\uc9c1 \uc0ac\uace0\ucc98\ub9ac \ub418\uc9c0 \uc54a\uace0 \uc788\uc74c.\"",
          "score": 0.8,
          "createdTime": [
            "2020-05-04",
            "9:12"
          ],
          "GPS": "37.48400741226237,126.77233709556346",
          "vid": "20"
        },
        {
          "contents": "\uacbd\uc778\ub85c \uc1a1\ub0b4\uc0ac\uac70\ub9ac\uc5d0\uc11c \uc911\ub3d9\ub85c \uc911\ub3d9\uc0ac\uac70\ub9ac\ucabd \uc88c\ud68c\uc804 \ucc28\ub7c9\ub4e4 \uc2e0\ud638 \ub450\uc138\ubc88.",
          "score": 0.8,
          "createdTime": [
            "2020-05-04",
            "8:28"
          ],
          "GPS": "37.48390511088493,126.76382642944907",
          "vid": "20"
        },
        {
          "contents": "\uacbd\uc778\ub85c \uc624\ub958\ub3d9\uc5ed\uc55e\uc0bc\uac70\ub9ac\uc5d0\uc11c \uace0\ucc99\uad50\uad50\ucc28\ub85c\uad6c\uac04 \uc815\uccb4.",
          "score": 0.8,
          "createdTime": [
            "2020-04-29",
            "7:48"
          ],
          "GPS": "37.4959241099598,126.84355189029216",
          "vid": "20"
        },
        {
          "contents": "\ubb34\ub124\ubbf8\ub85c \uad6c\uc0b0\uc0ac\uac70\ub9ac\uc5d0\uc11c \uc7a5\uc218\uc0ac\uac70\ub9ac\uad6c\uac04 \uc2e0\ud638 \ub450\ubc88.",
          "score": 0.8,
          "createdTime": [
            "2020-05-11",
            "10:34"
          ],
          "GPS": "37.483371621523375,126.75298524327305",
          "vid": "20"
        },
        {
          "contents": "\ubb34\ub124\ubbf8\ub85c \uc7a5\uc218\uace0\uac00\uad50\uc5d0\uc11c \uc7a5\uc218\ub098\ub4e4\ubaa9\uad6c\uac04 \uc815\uccb4.",
          "score": 0.8,
          "createdTime": [
            "2020-05-11",
            "14:48"
          ],
          "GPS": "37.4466131240147,126.74470676006516",
          "vid": "20"
        }
      ],
      "receivedData": [
        {
          "contents": "<\ucd5c\ucd08> \uacbd\uc6d0\ub300\ub85c \uc2b9\uae30\uc0ac\uac70\ub9ac\uc5d0\uc11c \uc2b9\ud559\uc0ac\uac70\ub9ac\uad6c\uac04 \uc2b9\ud559\uc0ac\uac70\ub9ac \uc57d 50m \ubabb \uac04 \uc9c0\uc810 2\ucc28\ub85c\uc5d0 \uace0\uc7a5\ub09c \uc2b9\uc6a9\ucc28\uac00 \uc138\uc6cc\uc838 \uc788\uc74c.",
          "score": 0.03,
          "createdTime": [
            "2020-04-29",
            "17:17"
          ],
          "GPS": "37.45080018516772,126.68992256473871",
          "vid": "4"
        }
      ]
    },
    "VTI": {
      "DR": 10.0,
      "AS": 1.8,
      "NT": 18846.43,
      "UR": 11.8,
      "VT": 571.5799999999999,
      "connectivity": 3490.08,
      "CF": 3,
      "VT_updateTime": 0,
      "PVT": 0
    },
    "RTI": [
      {
        "vid": "4",
        "VT": 0,
        "position": 3490.08,
        "updateTime": 0
      }
    ]
  }
}